setup.py
sergeymakinen/__init__.py
sergeymakinen/shell_utils.py
sergeymakinen.egg-info/PKG-INFO
sergeymakinen.egg-info/SOURCES.txt
sergeymakinen.egg-info/dependency_links.txt
sergeymakinen.egg-info/requires.txt
sergeymakinen.egg-info/top_level.txt
test/test.py