Metadata-Version: 1.1
Name: sergeymakinen
Version: 1.1.0b3
Summary: Sergey Makinen Python modules
Home-page: https://github.com/sergeymakinen/python-modules
Author: Sergey Makinen
Author-email: sergey@makinen.ru
License: MIT
Keywords: sergeymakinen library development
Platform: UNKNOWN
Classifier: Development Status :: 4 - Beta
Classifier: Intended Audience :: Developers
Classifier: Topic :: Software Development :: Libraries
Classifier: License :: OSI Approved :: MIT License
Classifier: Programming Language :: Python :: 3
Classifier: Programming Language :: Python :: 3.2
